sphviewer2/KDTree.py
sphviewer2/__init__.py
sphviewer2/sphviewer2.py
py_sphviewer2-1.1.0.dist-info/METADATA
py_sphviewer2-1.1.0.dist-info/WHEEL
py_sphviewer2-1.1.0.dist-info/top_level.txt
py_sphviewer2-1.1.0.dist-info/RECORD
