Metadata-Version: 2.1
Name: py-sphviewer2
Version: 1.1.0
Summary: A Python wrapper for SPH data rendering using the private smeshl C library. This versions performs the interpolation in a square grid.
Home-page: https://alejandrobll.github.io/content/sphviewer2/
Author: Alejandro Benitez-Llambay
Author-email: alejandro.benitezllambay@unimib.it
Project-URL: Bug Tracker, https://alejandrobll.github.io/content/sphviewer2/
Classifier: Programming Language :: Python :: 3
Classifier: License :: Other/Proprietary License
Classifier: Operating System :: OS Independent
Requires-Python: >=3.6
Requires-Dist: numpy>=1.18.0
